aind_hcr_data_loader/__init__.py
aind_hcr_data_loader/filters.py
aind_hcr_data_loader/hcr_dataset.py
aind_hcr_data_loader/s3_utils.py
aind_hcr_data_loader/tile_data.py
aind_hcr_data_loader/classifiers/simple_soma_1/__init__.py
aind_hcr_data_loader/classifiers/simple_soma_1/functions.py
aind_hcr_data_loader/classifiers/simple_soma_1/simple_soma_1.joblib
aind_hcr_data_loader/examples/749315_matched_cells_coreg.csv
aind_hcr_data_loader/examples/hcr_dataset_coreg.ipynb
aind_hcr_data_loader/examples/hcr_dataset_usage.ipynb
aind_hcr_data_loader/examples/mouse_config_example.json
aind_hcr_data_loader/examples/tile_data_usage.ipynb
aind_hcr_data_loader-0.4.0.dist-info/licenses/LICENSE
aind_hcr_data_loader-0.4.0.dist-info/METADATA
aind_hcr_data_loader-0.4.0.dist-info/WHEEL
aind_hcr_data_loader-0.4.0.dist-info/top_level.txt
aind_hcr_data_loader-0.4.0.dist-info/RECORD
