Metadata-Version: 2.4
Name: aind-hcr-data-loader
Version: 0.4.0
Summary: Generated from aind-library-template
Author: Allen Institute for Neural Dynamics
License: MIT
Classifier: Programming Language :: Python :: 3
Requires-Python: >=3.10
License-File: LICENSE
Requires-Dist: s3fs
Requires-Dist: numpy
Requires-Dist: dask[array]
Requires-Dist: zarr
Provides-Extra: dev
Requires-Dist: black; extra == "dev"
Requires-Dist: coverage; extra == "dev"
Requires-Dist: flake8; extra == "dev"
Requires-Dist: interrogate; extra == "dev"
Requires-Dist: isort; extra == "dev"
Requires-Dist: Sphinx; extra == "dev"
Requires-Dist: furo; extra == "dev"
Dynamic: license-file
